docs/_todos.md
docs/configurations.md
docs/environment.yml
docs/index.md
docs/quickstart_guide.md
docs/tracksuite_guide.md
docs/api/config.md
docs/api/data.md
docs/api/nodes.md
docs/api/scripts.md
docs/api/tools.md
docs/config/data_config.md
docs/config/deploy_data.md
docs/config/deploy_tools.md
docs/config/deployment.md
docs/config/host.md
docs/config/tools_config.md
docs/img/ECMWF_logo.svg
docs/img/deploy_data_family.png
docs/img/deploy_tools_family.png
docs/img/logo_tiny.ico
docs/img/mysuite.png
docs/scripts/gen-ref-pages.py
pyflow_wellies-1.2.0.dist-info/licenses/LICENSE
wellies/__init__.py
wellies/_version.py
wellies/config.py
wellies/data.py
wellies/deployment.py
wellies/exceptions.py
wellies/hosts.py
wellies/log_archiving.py
wellies/mars.py
wellies/quickstart.py
wellies/scripts.py
wellies/show_versions.py
wellies/tasks.py
wellies/tools.py
wellies/triggers.py
wellies/templates/build.sh_t
wellies/templates/config.py_t
wellies/templates/data.yaml_t
wellies/templates/deploy.py_t
wellies/templates/host.yaml_t
wellies/templates/nodes.py_t
wellies/templates/profiles.yaml_t
wellies/templates/test_configs.py_t
wellies/templates/tools.yaml_t
wellies/templates/user.yaml_t
pyflow_wellies-1.2.0.dist-info/METADATA
pyflow_wellies-1.2.0.dist-info/WHEEL
pyflow_wellies-1.2.0.dist-info/entry_points.txt
pyflow_wellies-1.2.0.dist-info/top_level.txt
pyflow_wellies-1.2.0.dist-info/RECORD
