Metadata-Version: 2.4
Name: pyflow-wellies
Version: 1.2.0
Summary: Collection of pyflow tools for ecflow suites
Author-email: Corentin Carton de Wiart <corentin.carton@ecmwf.int>
Maintainer-email: Juan Pereira Colonese <juan.colonese@ecmwf.int>
License: 
Project-URL: repository, https://github.com/ecmwf/pyflow-wellies
Project-URL: documentation, https://pyflow-wellies.readthedocs.io
Project-URL: issues, https://github.com/ecmwf/pyflow-wellies/issues
Classifier: Development Status :: 4 - Beta
Classifier: Intended Audience :: Science/Research
Classifier: License :: OSI Approved :: Apache Software License
Classifier: Natural Language :: English
Classifier: Operating System :: OS Independent
Classifier: Programming Language :: Python :: 3
Classifier: Programming Language :: Python :: 3 :: Only
Classifier: Programming Language :: Python :: 3.8
Classifier: Programming Language :: Python :: 3.10
Classifier: Topic :: Scientific/Engineering
Classifier: Topic :: Software Development :: Code Generators
Requires-Python: >=3.10
License-File: LICENSE
Requires-Dist: jinja2
Requires-Dist: pyyaml
Requires-Dist: pyflow-workflow-generator>=3.4.1
Requires-Dist: tracksuite>=0.4.1
Provides-Extra: test
Requires-Dist: pytest; extra == "test"
Provides-Extra: docs
Requires-Dist: mkdocs; extra == "docs"
Requires-Dist: mkdocs-material; extra == "docs"
Requires-Dist: mkdocstrings-python; extra == "docs"
Requires-Dist: mkdocs-autorefs; extra == "docs"
Requires-Dist: mkdocs-gen-files; extra == "docs"
Requires-Dist: pymdown-extensions; extra == "docs"
Requires-Dist: markdown-exec[ansi]; extra == "docs"
Dynamic: license-file
